apilens/__init__.py
apilens/anthropic_wrapper.py
apilens/base_wrapper.py
apilens/config.py
apilens/db.py
apilens/gemini_wrapper.py
apilens/logger.py
apilens/openai_wrapper.py
apilens/types.py
apilens-0.1.0.dist-info/licenses/LICENSE
apilens-0.1.0.dist-info/METADATA
apilens-0.1.0.dist-info/WHEEL
apilens-0.1.0.dist-info/top_level.txt
apilens-0.1.0.dist-info/RECORD
